{
  "androidId": 14,
  "androidMappingFromSdk": {
    "23": [
      "REFLEX_PLAY",
      "REFLEX_PLAY_PLUS",
      "TITAN_SMART_TALK",
      "REFLEX_VIBE",
      "REFLEX_HELLO",
      "REFLEX_VOX2",
      "FT_38081"
    ],
    "5": [
      "TITAN_90160"
    ],
    "15": [
      "REFLEX_3",
      "FT_38085",
      "FT_38100",
      "FT_38101",
      "FT_38102",
      "FT_38103",
      "FT_38104",
      "FT_38105",
      "FT_38106",
      "FT_38095",
      "TITAN_90166",
      "TITAN_90191",
      "TITAN_90196"
    ],
    "136": [
      "FT_38083",
      "FT_38084",
      "FT_38086",
      "FT_38096",
      "TITAN_90188"
    ],
    "115": [
      "TITAN_90197",
      "FT_38110",
      "FT_38111",
      "FT_38112"
    ],
    "32":[
      "FT_38107",
      "FT_38108",
      "FT_38109"
    ]
  },
  "androidMappingId": [],
  "category": "Weight Training",
  "iOSId": 15,
  "iOSMappingFromSdk": {
     "5": [
      "TITAN_90160"
    ],
    "23": [
      "REFLEX_PLAY",
      "REFLEX_PLAY_PLUS",
      "TITAN_SMART_TALK",
      "REFLEX_VIBE",
      "REFLEX_HELLO",
      "FT_38081",
      "REFLEX_VOX2"
    ],
    "15": [
      "REFLEX_3",
      "FT_38085",
      "FT_38100",
      "FT_38101",
      "FT_38102",
      "FT_38103",
      "FT_38104",
      "FT_38105",
      "FT_38106",
      "FT_38095",
      "TITAN_90166",
      "TITAN_90191",
      "TITAN_90196"
    ],
    "136": [
      "FT_38083",
      "FT_38084",
      "FT_38086",
      "TITAN_90188"
    ],
    "115": [
      "TITAN_90197",
      "FT_38110",
      "FT_38111",
      "FT_38112"
    ],
    "32":[
      "FT_38107",
      "FT_38108",
      "FT_38109"
    ]
  },
  "image": "ic_dumbbell",
  "name": "Dumbbell",
  "serverKey": [
    ""
  ],
  "strava": "",
  "type": "DUMBBELL"
}
